<Configuration ID="1936281a-92e9-4659-a82c-de1be7772c53">
  <Add OfficeClientEdition="64" Channel="MonthlyEnterprise" MigrateArch="TRUE">
    <Product ID="ProjectProRetail">
      <Language ID="en-us" />
      <Language ID="fi-fi" />
      <Language ID="MatchPreviousMSI" />
    </Product>
    <Product ID="LanguagePack">
      <Language ID="en-us" />
      <Language ID="fi-fi" />
      <Language ID="MatchPreviousMSI" />
    </Product>
    <Product ID="ProofingTools">
      <Language ID="fi-fi" />
    </Product>
  </Add>
  <Property Name="SharedComputerLicensing" Value="0" />
  <Property Name="PinIconsToTaskbar" Value="TRUE" />
  <Property Name="SCLCacheOverride" Value="0" />
  <Property Name="AUTOACTIVATE" Value="0" />
  <Property Name="FORCEAPPSHUTDOWN" Value="TRUE" />
  <Property Name="DeviceBasedLicensing" Value="0" />
  <Updates Enabled="TRUE" />
  <RemoveMSI />
  <AppSettings>
    <User Key="software\microsoft\office\16.0\common" Name="sendcustomerdata" Value="0" Type="REG_DWORD" App="office16" Id="L_Sendcustomerdata" />
  </AppSettings>
</Configuration>